README.txt
setup.cfg
setup.py
docs/CHANGES.txt
docs/CONTRIBUTORS.txt
docs/HISTORY.txt
docs/INSTALL.txt
docs/LICENSE.GPL
docs/LICENSE.txt
docs/README.txt
jalon/__init__.py
jalon.pas.sygefor.egg-info/PKG-INFO
jalon.pas.sygefor.egg-info/SOURCES.txt
jalon.pas.sygefor.egg-info/dependency_links.txt
jalon.pas.sygefor.egg-info/entry_points.txt
jalon.pas.sygefor.egg-info/namespace_packages.txt
jalon.pas.sygefor.egg-info/not-zip-safe
jalon.pas.sygefor.egg-info/paster_plugins.txt
jalon.pas.sygefor.egg-info/requires.txt
jalon.pas.sygefor.egg-info/top_level.txt
jalon/pas/__init__.py
jalon/pas/sygefor/README.txt
jalon/pas/sygefor/__init__.py
jalon/pas/sygefor/configure.zcml
jalon/pas/sygefor/install.py
jalon/pas/sygefor/interface.py
jalon/pas/sygefor/plugin.py
jalon/pas/sygefor/tests.py
jalon/pas/sygefor/browser/__init__.py
jalon/pas/sygefor/browser/add_plugin.zpt
jalon/pas/sygefor/browser/configure.zcml
jalon/pas/sygefor/browser/icon.gif
jalon/pas/sygefor/models/SygeForUser.py
jalon/pas/sygefor/models/__init__.py
jalon/pas/sygefor/plugins/__init__.py