Metadata-Version: 1.0
Name: jalon.pas.sygefor
Version: 1.1
Summary: A pas Plugin for SygeFor connexion
Home-page: http://svn.plone.org/svn/collective/
Author: Bordonado Christophe - Université Nice Sophia Antipolis (uns) Service TICE
Author-email: tice@unice.fr
License: GPL
Platform: UNKNOWN
Classifier: Framework :: Plone
Classifier: Intended Audience :: Developers
Classifier: License :: OSI Approved :: GNU General Public License (GPL)
